{"moduleName":null,"summaries":[{"symbol":{"__symbol":0,"members":[]},"metadata":{"__symbolic":"class","members":{"_container":[{"__symbolic":"property","decorators":[{"__symbolic":"call","expression":{"__symbolic":"resolved","symbol":{"__symbol":1,"members":[]},"line":21,"character":3,"fileName":"build\\tools\\text-edit-tool\\text-edit-tool.component.ts"},"arguments":["container"]}]}],"_textArea":[{"__symbolic":"property","decorators":[{"__symbolic":"call","expression":{"__symbolic":"resolved","symbol":{"__symbol":1,"members":[]},"line":22,"character":3,"fileName":"build\\tools\\text-edit-tool\\text-edit-tool.component.ts"},"arguments":["textArea"]}]}],"__ctor__":[{"__symbolic":"constructor","parameters":[{"__symbolic":"resolved","symbol":{"__symbol":2,"members":[]},"line":48,"character":26,"fileName":"build\\tools\\text-edit-tool\\text-edit-tool.component.ts"},{"__symbolic":"resolved","symbol":{"__symbol":3,"members":[]},"line":49,"character":35,"fileName":"build\\tools\\text-edit-tool\\text-edit-tool.component.ts"},{"__symbolic":"resolved","symbol":{"__symbol":4,"members":[]},"line":50,"character":25,"fileName":"build\\tools\\text-edit-tool\\text-edit-tool.component.ts"}]}],"onTextAreaInput":[{"__symbolic":"method"}],"onTextAreaLoaded":[{"__symbolic":"method"}],"onClick":[{"__symbolic":"method"}],"pixelizeBounds":[{"__symbolic":"method"}],"divify":[{"__symbolic":"method"}],"ngOnInit":[{"__symbolic":"method"}],"finalize":[{"__symbolic":"method"}],"getTop":[{"__symbolic":"method"}],"getBottom":[{"__symbolic":"method"}],"getLeft":[{"__symbolic":"method"}],"getRight":[{"__symbolic":"method"}],"getMarginTop":[{"__symbolic":"method"}],"getMarginLeft":[{"__symbolic":"method"}],"getHAlign":[{"__symbolic":"method"}]}},"type":{"summaryKind":1,"type":{"reference":{"__symbol":0,"members":[]},"diDeps":[{"isAttribute":false,"isHost":false,"isSelf":false,"isSkipSelf":false,"isOptional":false,"token":{"identifier":{"reference":{"__symbol":2,"members":[]}}}},{"isAttribute":false,"isHost":false,"isSelf":false,"isSkipSelf":false,"isOptional":false,"token":{"identifier":{"reference":{"__symbol":3,"members":[]}}}},{"isAttribute":false,"isHost":false,"isSelf":false,"isSkipSelf":false,"isOptional":false,"token":{"identifier":{"reference":{"__symbol":4,"members":[]}}}}],"lifecycleHooks":[0]},"isComponent":true,"selector":"app-text-edit-tool","exportAs":null,"inputs":{},"outputs":{},"hostListeners":{},"hostProperties":{},"hostAttributes":{},"providers":[],"viewProviders":[],"queries":[],"guards":{},"viewQueries":[{"selectors":[{"value":"container"}],"first":true,"descendants":true,"propertyName":"_container","read":null},{"selectors":[{"value":"textArea"}],"first":true,"descendants":true,"propertyName":"_textArea","read":null}],"entryComponents":[],"changeDetection":1,"template":{"ngContentSelectors":[],"encapsulation":0},"componentViewType":{"__symbol":5,"members":[]},"rendererType":{"__symbol":6,"members":[]},"componentFactory":{"__symbol":7,"members":[]}}}],"symbols":[{"__symbol":0,"name":"TextEditToolComponent","filePath":"./text-edit-tool.component"},{"__symbol":1,"name":"ViewChild","filePath":"@angular/core/core"},{"__symbol":2,"name":"DataStoreService","filePath":"../../services/data-store.service"},{"__symbol":3,"name":"TextRenderingService","filePath":"../../services/text-rendering.service"},{"__symbol":4,"name":"ElementRef","filePath":"@angular/core/core"},{"__symbol":5,"name":"View_TextEditToolComponent_0","filePath":"./text-edit-tool.component.ngfactory"},{"__symbol":6,"name":"RenderType_TextEditToolComponent","filePath":"./text-edit-tool.component.ngfactory"},{"__symbol":7,"name":"TextEditToolComponentNgFactory","filePath":"./text-edit-tool.component.ngfactory"}]}